qibochem/__init__.py
qibochem/ansatz/__init__.py
qibochem/ansatz/basis_rotation.py
qibochem/ansatz/hardware_efficient.py
qibochem/ansatz/hf_reference.py
qibochem/ansatz/ucc.py
qibochem/driver/__init__.py
qibochem/driver/hamiltonian.py
qibochem/driver/molecule.py
qibochem/measurement/__init__.py
qibochem/measurement/optimization.py
qibochem/measurement/result.py
qibochem-0.0.3.dist-info/LICENSE
qibochem-0.0.3.dist-info/METADATA
qibochem-0.0.3.dist-info/WHEEL
qibochem-0.0.3.dist-info/RECORD
