Metadata-Version: 2.1
Name: qibochem
Version: 0.0.3
Summary: Quantum chemistry module for quantum computing with Qibo
Home-page: https://github.com/qiboteam/qibochem/
License: Apache-2.0
Author: The Qibo team
Requires-Python: >=3.9,<3.12
Classifier: License :: OSI Approved :: Apache Software License
Classifier: Programming Language :: Python :: 3
Classifier: Programming Language :: Python :: 3.9
Classifier: Programming Language :: Python :: 3.10
Classifier: Programming Language :: Python :: 3.11
Classifier: Topic :: Scientific/Engineering :: Chemistry
Requires-Dist: openfermion (>=1.5,<2.0)
Requires-Dist: pyscf (>=2.4.0,<3.0.0)
Requires-Dist: qibo (>=0.2.0)
Requires-Dist: scipy (>=1.10.1,<2.0.0)
Project-URL: Documentation, https://qibo.science/qibochem/stable
Project-URL: Repository, https://github.com/qiboteam/qibochem/
